newpipelist.py
newpipelist-1.0.dist-info/LICENSE.txt
newpipelist-1.0.dist-info/METADATA
newpipelist-1.0.dist-info/WHEEL
newpipelist-1.0.dist-info/entry_points.txt
newpipelist-1.0.dist-info/top_level.txt
newpipelist-1.0.dist-info/RECORD
