Metadata-Version: 2.1
Name: newpipelist
Version: 1.0
Summary: A utility to convert playlists in a NewPipe database export to M3U files
Home-page: https://tilde.club/~gwymor/newpipelist
Author: Gwyneth Morgan
Author-email: gwymor@tilde.club
License: UNKNOWN
Platform: UNKNOWN
Classifier: Programming Language :: Python :: 3
Classifier: License :: OSI Approved :: MIT License
Classifier: Operating System :: OS Independent
License-File: LICENSE.txt
